Metadata-Version: 1.0
Name: jbird
Version: 0.0.4
Summary: Key/value data storage
Home-page: UNKNOWN
Author: UNKNOWN
Author-email: notdepot@gmail.com
License: UNKNOWN
Platform: UNKNOWN
